tests/__init__.py
tests/test_encoder.py
vniencoder/__init__.py
vniencoder/encoder.py
vniencoder-0.2.1.dist-info/LICENSE
vniencoder-0.2.1.dist-info/METADATA
vniencoder-0.2.1.dist-info/WHEEL
vniencoder-0.2.1.dist-info/top_level.txt
vniencoder-0.2.1.dist-info/RECORD
