Metadata-Version: 2.2
Name: vniencoder
Version: 0.2.1
Summary: Thư viện mã hóa và giải mã văn bản tiếng Việt theo VNI
Home-page: https://github.com/Tkag0001/vniencoder
Author: Trịnh Huỳnh Thịnh Khang
Author-email: trinhhuynhthinhkhang.work@gmail.com
License: MIT
Classifier: Programming Language :: Python :: 3
Classifier: License :: OSI Approved :: MIT License
Classifier: Operating System :: OS Independent
Requires-Python: >=3.6
License-File: LICENSE
Requires-Dist: bogo
